.editorconfig
.gitignore
MANIFEST.in
README.rst
Supported.md
Unsupported.md
_generate_supported_list.py
_setup_info_generated.py
requirements.txt
setup.py
examples/.gitignore
examples/README.md
examples/_setup_env.py
examples/conformer/README.md
examples/conformer/_setup_env.py
examples/conformer/conformer.py
examples/conformer/main.py
examples/mnist/README.md
examples/mnist/_setup_env.py
examples/mnist/main.py
examples/mnist/model.py
examples/mnist/requirements.txt
examples/parallel_wavegan/.gitignore
examples/parallel_wavegan/README.md
examples/parallel_wavegan/_setup_env.py
examples/parallel_wavegan/decoder.py
examples/parallel_wavegan/mb_melgan.v2.yaml
examples/parallel_wavegan/pytorch_to_returnn.py
examples/parallel_wavegan/requirements.txt
examples/parallel_wavegan/tacotron2_ljspeech.config.py
examples/word_language_model/README.md
examples/word_language_model/_setup_env.py
examples/word_language_model/convert_and_verify.py
examples/word_language_model/data.py
examples/word_language_model/generate.py
examples/word_language_model/main.py
examples/word_language_model/model.py
examples/word_language_model/requirements.txt
pytorch_to_returnn/README.md
pytorch_to_returnn/__init__.py
pytorch_to_returnn/__setup__.py
pytorch_to_returnn/log.py
pytorch_to_returnn/pprint.py
pytorch_to_returnn.egg-info/PKG-INFO
pytorch_to_returnn.egg-info/SOURCES.txt
pytorch_to_returnn.egg-info/dependency_links.txt
pytorch_to_returnn.egg-info/requires.txt
pytorch_to_returnn.egg-info/top_level.txt
pytorch_to_returnn/converter/README.md
pytorch_to_returnn/converter/__init__.py
pytorch_to_returnn/converter/converter.py
pytorch_to_returnn/converter/utils.py
pytorch_to_returnn/import_wrapper/README.rst
pytorch_to_returnn/import_wrapper/__init__.py
pytorch_to_returnn/import_wrapper/ast_transformer.py
pytorch_to_returnn/import_wrapper/context.py
pytorch_to_returnn/import_wrapper/default_importers.py
pytorch_to_returnn/import_wrapper/import_.py
pytorch_to_returnn/import_wrapper/mod_map.py
pytorch_to_returnn/import_wrapper/wrap.py
pytorch_to_returnn/import_wrapper/base_wrappers/__init__.py
pytorch_to_returnn/import_wrapper/base_wrappers/class_.py
